README.md
setup.py
alibabacloud_ccp_credentials/__init__.py
alibabacloud_ccp_credentials/client.py
alibabacloud_ccp_credentials/models.py
alibabacloud_ccp_credentials.egg-info/PKG-INFO
alibabacloud_ccp_credentials.egg-info/SOURCES.txt
alibabacloud_ccp_credentials.egg-info/dependency_links.txt
alibabacloud_ccp_credentials.egg-info/requires.txt
alibabacloud_ccp_credentials.egg-info/top_level.txt